{"status":"success","response":[{"id":"true_5524981122626@c.us_3EB0D4DD81B5B4FDAD2AFF","viewed":false,"body":"Teste AgendaPro ✅","type":"chat","subtype":null,"t":1754792955,"from":"553591947159@c.us","to":"5524981122626@c.us","ack":1,"isNewMsg":true,"star":false,"kicNotified":false,"isFromTemplate":false,"pollInvalidated":false,"isSentCagPollCreation":false,"latestEditMsgKey":null,"latestEditSenderTimestampMs":null,"mentionedJidList":[],"groupMentions":[],"isEventCanceled":false,"eventInvalidated":false,"urlText":null,"urlNumber":null,"isVcardOverMmsDocument":false,"isForwarded":false,"isQuestion":false,"hasReaction":false,"disappearingModeInitiator":"chat","disappearingModeTrigger":"chat_settings","productHeaderImageRejected":false,"lastPlaybackProgress":0,"isDynamicReplyButtonsMsg":false,"isCarouselCard":false,"parentMsgId":null,"callSilenceReason":null,"isVideoCall":false,"callDuration":null,"callCreator":null,"callParticipants":null,"isCallLink":null,"callLinkToken":null,"isMdHistoryMsg":false,"stickerSentTs":0,"isAvatar":false,"lastUpdateFromServerTs":0,"invokedBotWid":null,"bizBotType":null,"botResponseTargetId":null,"botPluginType":null,"botPluginReferenceIndex":null,"botPluginSearchProvider":null,"botPluginSearchUrl":null,"botPluginSearchQuery":null,"botPluginMaybeParent":false,"botReelPluginThumbnailCdnUrl":null,"botMessageDisclaimerText":null,"botMsgBodyType":null,"requiresDirectConnection":false,"bizContentPlaceholderType":null,"hostedBizEncStateMismatch":false,"senderOrRecipientAccountTypeHosted":false,"placeholderCreatedWhenAccountIsHosted":false,"chatId":"5524981122626@c.us","fromMe":true,"sender":{"id":"553591947159@c.us","pushname":"Wesley Abreu","type":"in","isBusiness":false,"isEnterprise":false,"isSmb":false,"textStatusLastUpdateTime":-1,"syncToAddressbook":false,"formattedName":"You","isMe":true,"isMyContact":false,"isPSA":false,"isUser":true,"isWAContact":true,"profilePicThumbObj":null,"msgs":null},"timestamp":1754792955,"content":"Teste AgendaPro ✅","isGroupMsg":false,"mediaData":{}}],"mapper":"return","session":"agendapro"}